Metadata-Version: 2.4
Name: types-seaborn
Version: 0.13.2.20251221
Summary: Typing stubs for seaborn
License-Expression: Apache-2.0
Project-URL: Homepage, https://github.com/python/typeshed
Project-URL: GitHub, https://github.com/python/typeshed
Project-URL: Changes, https://github.com/typeshed-internal/stub_uploader/blob/main/data/changelogs/seaborn.md
Project-URL: Issue tracker, https://github.com/python/typeshed/issues
Project-URL: Chat, https://gitter.im/python/typing
Classifier: Programming Language :: Python :: 3
Classifier: Typing :: Stubs Only
Requires-Python: >=3.9
License-File: LICENSE
Requires-Dist: matplotlib>=3.8
Requires-Dist: numpy>=1.20
Requires-Dist: pandas-stubs
Dynamic: license-file
